treespec/__init__.py
treespec/conf/__init__.py
treespec/conf/config.py
treespec/conf/config_parser.py
treespec/datasets/__init__.py
treespec/datasets/image_dataset.py
treespec/models/__init__.py
treespec/models/classification_model.py
treespec/scripts/__init__.py
treespec/scripts/create_essen_dataset.py
treespec/scripts/match_predicted_species.py
treespec/scripts/matching.py
treespec/scripts/sauen_csv_adjuster.py
treespec/scripts/train.py
treespec/utils/__init__.py
treespec/utils/image_tools.py
treespec/utils/matching_tools.py
treespec-0.1.0.dist-info/licenses/LICENSE
treespec-0.1.0.dist-info/METADATA
treespec-0.1.0.dist-info/WHEEL
treespec-0.1.0.dist-info/top_level.txt
treespec-0.1.0.dist-info/RECORD
