Metadata-Version: 2.4
Name: treespec
Version: 0.1.0
Summary: A deeplearning pipeline to classify tree species in terrestrial panorama pictures.
Author-email: Ingmar Vogel <ingmar.vogel@student.hpi.uni-potsdam.de>
License: Copyright (c) 2025 Ingmar Vogel
Project-URL: Homepage, https://github.com/vogelingmar/treespec
Keywords: images,deep learning
Classifier: Programming Language :: Python
Classifier: Programming Language :: Python :: 3
License-File: LICENSE
Requires-Dist: torch
Requires-Dist: torchvision
Requires-Dist: pytorch-lightning
Requires-Dist: opencv-python
Requires-Dist: dataclasses
Requires-Dist: py360convert
Requires-Dist: scikit-image
Requires-Dist: imageio
Requires-Dist: scipy
Requires-Dist: pyshp
Provides-Extra: dev
Requires-Dist: black; extra == "dev"
Requires-Dist: mypy; extra == "dev"
Requires-Dist: pylint; extra == "dev"
Requires-Dist: pytest; extra == "dev"
Requires-Dist: pytest-cov; extra == "dev"
Provides-Extra: docs
Requires-Dist: sphinx; extra == "docs"
Requires-Dist: sphinx-copybutton; extra == "docs"
Requires-Dist: sphinx-design; extra == "docs"
Requires-Dist: sphinx-docsearch; extra == "docs"
Requires-Dist: sphinxawesome-theme; extra == "docs"
Requires-Dist: sphinx-sitemap; extra == "docs"
Requires-Dist: sphinxcontrib-jsmath; extra == "docs"
Requires-Dist: sphinxcontrib-katex; extra == "docs"
Requires-Dist: sphinxcontrib-napoleon; extra == "docs"
Requires-Dist: sphinx_mdinclude; extra == "docs"
Dynamic: license-file
